portableenv/__init__.py
portableenv/__main__.py
portableenv/cli.py
portableenv/env_manager.py
portableenv-2.0.4.dist-info/LICENSE
portableenv-2.0.4.dist-info/METADATA
portableenv-2.0.4.dist-info/WHEEL
portableenv-2.0.4.dist-info/entry_points.txt
portableenv-2.0.4.dist-info/top_level.txt
portableenv-2.0.4.dist-info/RECORD
