Metadata-Version: 2.1
Name: portableenv
Version: 2.0.4
Summary: A tool to create virtual environments using an embedded Python interpreter.
Home-page: https://github.com/abdulrahimpds/portableenv
Author: AbdulRahim Khan
Author-email: abdulrahimpds@gmail.com
Classifier: Programming Language :: Python :: 3.7
Classifier: Programming Language :: Python :: 3.8
Classifier: License :: OSI Approved :: MIT License
Requires-Python: >=3.7
License-File: LICENSE
Requires-Dist: virtualenv
Requires-Dist: click
